{
    "data": [
        {
            "title": "韩国计划三季度对中国团体旅客免签 外交部回应",
            "id": "1599680",
            "description": "人民财讯3月21日电，3月21日，外交部发言人毛宁主持例行记者会。有记者提问，韩国计划第三季度对中国团体旅客免签，中方对此如何评价，有何期待？毛宁表示，中韩是近邻，加强人文交流，符合双方利益。（央视新闻）",
            "link": "https://www.stcn.com/article/detail/1599680.html",
            "pub_date": "2025-03-21 15:28:15",
            "source": "stcn",
            "kind": 2,
            "language": "zh-CN"
        },
        {
            "title": "蔚来法务部：多名黑公关抢发黑文被立案调查",
            "id": "1599682",
            "description": "人民财讯3月21日电，蔚来法务部3月21日发文称，近一年来，蔚来法务部已陆续公布数起警方侦办涉蔚来谣言案件，多名违法人员已被行政拘留和处罚，同时多名违法人员在诉讼中败诉被法院认定侵权。目前还有多起违法案件公安已立案，部分案件警方已抓获或锁定违法人员，案件正在调查当中。另有十余起案件正在民事诉讼当中，近期会公布部分案件进展。继近期通报过的“鹿姐说车”失误提前发布造谣黑文案被立案调查、“69云购车 | 蔚来”造谣被公安机关处罚后，蔚来法务部监测到又有多名黑公关“抢跑”发布造谣抹黑蔚来文案，意图在蔚来ET9正式交付时对蔚来品牌和旗下产品进行恶意攻击，公司均已报警，公安机关已立案调查。",
            "link": "https://www.stcn.com/article/detail/1599682.html",
            "pub_date": "2025-03-21 15:28:42",
            "source": "stcn",
            "kind": 2,
            "language": "zh-CN"
        },
        {
            "title": "广州正式启动首批配售型保障房申购意向预登记工作",
            "id": "1599669",
            "description": "人民财讯3月21日电，据广州发布，3月21日上午，广州正式启动首批配售型保障房申购意向预登记工作，成为国内第一个推出配售型保障房的一线城市。首批推出的两个项目为：萝岗和苑、嘉翠苑，销售基准价分别为15800元/平方米、17300元/平方米，都是地铁盘，数量分别为936套、400套，全部为现楼。配售型保障房是面向本市户籍住房困难家庭和各类引进人才等工薪收入群体销售的保障性住房，实施封闭管理，禁止变更为商品房流入市场，出售（对象为合资格申购者）价格不得高于原购房价格，回购（对象为建设运营机构）价格按照原购房价格每年扣减1%计算。本次申购意向预登记的配售性保障性住房项目将于近期发布销售公告。",
            "link": "https://www.stcn.com/article/detail/1599669.html",
            "pub_date": "2025-03-21 15:11:13",
            "source": "stcn",
            "kind": 2,
            "language": "zh-CN"
        },
        {
            "title": "山东路桥成立工程装备新公司 含物联网业务",
            "id": "1599671",
            "description": "人民财讯3月21日电，企查查APP显示，近日，山东高速工程装备有限公司成立，法定代表人为王林洲，注册资本10亿元，经营范围包含：物联网应用服务；物联网技术服务；招投标代理服务等。企查查股权穿透显示，该公司由山东路桥全资持股。",
            "link": "https://www.stcn.com/article/detail/1599671.html",
            "pub_date": "2025-03-21 15:12:06",
            "source": "stcn",
            "kind": 2,
            "language": "zh-CN"
        },
        {
            "title": "华电国际等在天津成立电力能源合伙企业",
            "id": "1599673",
            "description": "人民财讯3月21日电，企查查APP显示，近日，华豫二期（天津）电力能源合伙企业（有限合伙）成立，经营范围包含：发电业务、输电业务、供（配）电业务；发电技术服务。企查查股权穿透显示，该企业由华电国际等共同出资。",
            "link": "https://www.stcn.com/article/detail/1599673.html",
            "pub_date": "2025-03-21 15:12:53",
            "source": "stcn",
            "kind": 2,
            "language": "zh-CN"
        },
        {
            "title": "深交所唐瑞：研究优化险资入市的机制，支持保险资金加大权益投资",
            "id": "1599674",
            "description": "人民财讯3月21日电，3月21日，深交所以“新格局下的行业发展”为主题举办第三期ETF生态大会。会上，党委委员、副总经理唐瑞表示，深交所将持续推动持续提升上市公司质量，研究优化险资入市的机制，减少交易摩擦，支持保险资金加大权益投资。同时，针对中长期资金需求，丰富低波产品矩阵。唐瑞透露，深交所正在制定服务中长期资金入市相关工作方案，围绕完善产品供给、优化环境、对接服务等关键领域，重点解决中长期资金“买什么”“买得好”等问题。深交所将持续推动持续提升上市公司质量，研究优化险资入市的机制，减少交易摩擦，支持保险资金加大权益投资。针对中长期资金需求，丰富低波产品矩阵。推动行业由推广单一产品向推广投资策略组合转变，推出“大话策略”服务体系，重点推广定投策略，引导形成“长钱长投”的市场氛围。（中证金牛座）",
            "link": "https://www.stcn.com/article/detail/1599674.html",
            "pub_date": "2025-03-21 15:13:37",
            "source": "stcn",
            "kind": 2,
            "language": "zh-CN"
        },
        {
            "title": "中国中铁等在南京成立商贸投资发展公司",
            "id": "1599676",
            "description": "人民财讯3月21日电，企查查APP显示，近日，南京铁工商贸投资发展有限公司成立，法定代表人为东树人，注册资本为2亿元，经营范围包含：道路货物运输（不含危险货物）；房地产开发经营；建设工程施工；以自有资金从事投资活动；规划设计管理等。企查查股权穿透显示，该公司由中国中铁旗下中国铁工投资建设集团有限公司、南京江宁商务商贸发展集团有限公司共同持股。",
            "link": "https://www.stcn.com/article/detail/1599676.html",
            "pub_date": "2025-03-21 15:13:54",
            "source": "stcn",
            "kind": 2,
            "language": "zh-CN"
        },
        {
            "title": "三部门印发儿童友好城市建设经验举措",
            "id": "1599644",
            "description": "人民财讯3月21日电，国家发展改革委办公厅、国务院妇儿工委办公室、住房城乡建设部办公厅发布《关于印发儿童友好城市建设经验举措》的通知。各地要结合自身实际，主动对标先进，跟进学习借鉴，及时总结在改革创新和实践探索中涌现出的好经验好做法，加强工作成果交流和复制推广，实现经验做法的创新性转化和差别化探索。各地发展改革、妇女儿童工作、住房城乡建设部门要加强组织领导和工作统筹，指导相关城市深化体制机制改革，完善建设路径模式，进一步提升建设质量成效。对于具有重大创新的建设模式和有益做法，及时向国家发展改革委、国务院妇儿工委办公室、住房城乡建设部报送。",
            "link": "https://www.stcn.com/article/detail/1599644.html",
            "pub_date": "2025-03-21 15:03:00",
            "source": "stcn",
            "kind": 2,
            "language": "zh-CN"
        },
        {
            "title": "收评：创业板指跌2.17% 全市场逾4300只个股下跌",
            "id": "1599647",
            "description": "人民财讯3月21日电，3月21日，三大指数集体收跌，创业板领跌。截至收盘，沪指跌1.29%，深证成指跌1.76%，创业板指跌2.17%。盘面上看，人形机器人、汽车、芯片板块跌幅居前，黄金概念股回调；深海科技概念股逆势大涨，巨力索具7连板；水产品板块表现活跃，开创国际涨停；能源设备、钢铁、港口等板块涨幅居前。全市场逾4300只个股下跌，成交金额逾1.5万亿元。北证50指数跌超4%。",
            "link": "https://www.stcn.com/article/detail/1599647.html",
            "pub_date": "2025-03-21 15:05:04",
            "source": "stcn",
            "kind": 2,
            "language": "zh-CN"
        },
        {
            "title": "财政部副部长廖岷会见香港证监会行政总裁梁凤仪",
            "id": "1599651",
            "description": "人民财讯3月21日电，3月19日，财政部副部长廖岷在京会见香港证监会行政总裁梁凤仪，双方主要就深化内地与香港资本市场合作等议题交换意见。 廖岷表示，长期以来，财政部按照党中央、国务院决策部署，坚决支持巩固提升香港国际金融中心地位，未来将继续支持香港发展经济，改善民生，更好融入国家发展大局。 梁凤仪表示，感谢财政部多年来对香港资本市场发展的支持，香港证监会将继续发挥积极作用，进一步推动两地资本市场协同发展。",
            "link": "https://www.stcn.com/article/detail/1599651.html",
            "pub_date": "2025-03-21 15:06:11",
            "source": "stcn",
            "kind": 2,
            "language": "zh-CN"
        },
        {
            "title": "葡萄牙国务部长兼外长兰热尔将访华",
            "id": "1599653",
            "description": "人民财讯3月21日电，外交部发言人宣布：应中共中央政治局委员、外交部长王毅邀请，葡萄牙国务部长兼外长兰热尔将于3月24日至28日访华。其间，两国外长将举行中葡第二次外长级战略对话。",
            "link": "https://www.stcn.com/article/detail/1599653.html",
            "pub_date": "2025-03-21 15:06:48",
            "source": "stcn",
            "kind": 2,
            "language": "zh-CN"
        },
        {
            "title": "紫江企业在河北新设包装材料公司",
            "id": "1599655",
            "description": "人民财讯3月21日电，企查查APP显示，近日，河北紫江包装材料有限公司成立，法定代表人为孙军，经营范围包含：塑料包装箱及容器制造；食品用塑料包装容器工具制品销售等。企查查股权穿透显示，该公司由紫江企业全资持股。",
            "link": "https://www.stcn.com/article/detail/1599655.html",
            "pub_date": "2025-03-21 15:07:00",
            "source": "stcn",
            "kind": 2,
            "language": "zh-CN"
        },
        {
            "title": "建设银行：近期国内外贵金属价格波动加剧，市场风险提升",
            "id": "1599657",
            "description": "人民财讯3月21日电，建设银行发布关于近期贵金属业务市场风险提示的公告，近期国内外贵金属价格波动加剧，市场风险提升。请提高贵金属业务的风险防范意识，合理控制仓位，及时关注持仓情况和保证金余额变化情况，理性投资。",
            "link": "https://www.stcn.com/article/detail/1599657.html",
            "pub_date": "2025-03-21 15:09:46",
            "source": "stcn",
            "kind": 2,
            "language": "zh-CN"
        },
        {
            "title": "国内商品期货收盘 集运欧线涨超2%",
            "id": "1599659",
            "description": "人民财讯3月21日电，国内商品期货收盘，SC原油、低硫燃料油、集运欧线涨超2%，燃料油、沥青涨超1%；纸浆跌近2%，菜粕、沪银、焦炭、焦煤跌超1%。",
            "link": "https://www.stcn.com/article/detail/1599659.html",
            "pub_date": "2025-03-21 15:09:56",
            "source": "stcn",
            "kind": 2,
            "language": "zh-CN"
        },
        {
            "title": "智微智能成立新公司 含电子产品销售业务",
            "id": "1599661",
            "description": "人民财讯3月21日电，企查查APP显示，近日，深圳市艾玮智途科技有限公司成立，法定代表人为袁微微，注册资本100万，经营范围包含：电子产品销售；信息技术咨询服务；网络设备制造；网络设备销售等。企查查股权穿透显示，该公司由智微智能全资持股。",
            "link": "https://www.stcn.com/article/detail/1599661.html",
            "pub_date": "2025-03-21 15:10:09",
            "source": "stcn",
            "kind": 2,
            "language": "zh-CN"
        },
        {
            "title": "港股医药板块走弱，多只ETF跌超4%",
            "id": "1599631",
            "description": "人民财讯3月21日电，港股医药板块尾盘继续走弱，多只ETF跌超4%，截至发稿，银华国证港股通创新药ETF跌4.84%，汇添富国证港股通创新药ETF跌4.64%，广发中证香港创新药ETF跌4.69%，景顺长城中证港股通创新药ETF跌4.43%，华泰柏瑞恒生创新药ETF跌4.44%。",
            "link": "https://www.stcn.com/article/detail/1599631.html",
            "pub_date": "2025-03-21 14:52:12",
            "source": "stcn",
            "kind": 2,
            "language": "zh-CN"
        },
        {
            "title": "日科化学成立高分子材料新公司",
            "id": "1599633",
            "description": "人民财讯3月21日电，企查查APP显示，近日，山东日科高分子材料有限公司成立，法定代表人为刘大伟，注册资本1000万元，经营范围包含：新材料技术研发；生物基材料技术研发；生物基材料聚合技术研发；机械设备研发等。企查查股权穿透显示，该公司由日科化学全资持股。",
            "link": "https://www.stcn.com/article/detail/1599633.html",
            "pub_date": "2025-03-21 14:52:23",
            "source": "stcn",
            "kind": 2,
            "language": "zh-CN"
        },
        {
            "title": "京威股份新设子公司 含电池制造业务",
            "id": "1599635",
            "description": "人民财讯3月21日电，企查查APP显示，近日，北京峰璟能源科技有限公司成立，法定代表人为李璟瑜，经营范围包含：电池制造；电池销售；电池零配件生产；电池零配件销售等。企查查股权穿透显示，该公司由京威股份全资持股。",
            "link": "https://www.stcn.com/article/detail/1599635.html",
            "pub_date": "2025-03-21 14:52:56",
            "source": "stcn",
            "kind": 2,
            "language": "zh-CN"
        },
        {
            "title": "日本核心CPI连续42个月同比上升",
            "id": "1599637",
            "description": "人民财讯3月21日电，日本总务省21日公布的报告显示，今年2月，日本去除生鲜食品后的核心消费价格指数（CPI）同比上升3.0%至109.7，连续42个月同比上升。报告显示，食品价格全面上涨，成为拉动日本物价上涨的最主要原因。2月，日本民众餐桌上不可或缺的卷心菜价格同比上涨130.5%；去年夏季开始出现的“大米荒”并未因政府宣布向市场投放储备米而缓解，普通粳米价格同比涨幅达81.4%。（新华社）",
            "link": "https://www.stcn.com/article/detail/1599637.html",
            "pub_date": "2025-03-21 14:58:40",
            "source": "stcn",
            "kind": 2,
            "language": "zh-CN"
        },
        {
            "title": "亚康股份投资成立信息技术新公司",
            "id": "1599639",
            "description": "人民财讯3月21日电，企查查APP显示，近日，亚康万玮信息技术（怀来）有限公司成立，法定代表人为王丰，经营范围包含：信息技术咨询服务；信息系统运行维护服务；大数据服务；数据处理和存储支持服务等。企查查股权穿透显示，该公司由亚康股份全资持股。",
            "link": "https://www.stcn.com/article/detail/1599639.html",
            "pub_date": "2025-03-21 14:58:52",
            "source": "stcn",
            "kind": 2,
            "language": "zh-CN"
        }
    ]
}