{
    "data": [
        {
            "title": "华控赛格：间接控股股东延期履行避免同业竞争承诺事项",
            "id": "2039997",
            "description": "人民财讯6月13日电，华控赛格(000068)6月13日晚间公告，公司间接控股股东山西建设投资集团有限公司（简称“山西建投”）5年承诺期即将到期，公司近日收到其出具的《关于延期履行避免同业竞争的承诺函》，拟将相关承诺履行期限延期3年。",
            "link": "https://www.stcn.com/article/detail/2039997.html",
            "pub_date": "2025-06-13 20:02:38",
            "source": "stcn",
            "kind": 2,
            "language": "zh-CN"
        },
        {
            "title": "瑞普生物：拟1.15亿元转让中岸生物48.42%股权",
            "id": "2040007",
            "description": "人民财讯6月13日电，瑞普生物(300119)6月13日晚间公告，公司拟将控股子公司中岸生物48.42%股权转让给江西双胞胎生物技术有限公司，交易价1.15亿元。此次交易涉及中岸生物负责实施的募投项目“中岸生物改扩建项目”，目前该项目已达到预定可使用状态并已结项。此次交易完成后，公司持有中岸生物20%股权，中岸生物不再纳入公司合并报表范围。此次通过中岸生物股权转让引入战略合作伙伴，是公司主动布局产业链生态的重要举措，双方将在疫苗、药物研发、产品采购、疫病防治等领域建立长期战略伙伴关系。",
            "link": "https://www.stcn.com/article/detail/2040007.html",
            "pub_date": "2025-06-13 20:07:03",
            "source": "stcn",
            "kind": 2,
            "language": "zh-CN"
        },
        {
            "title": "特朗普威胁伊朗下一波打击“更残酷”",
            "id": "2040008",
            "description": "人民财讯6月13日电，美国总统特朗普13日在社交媒体上警告伊朗，下一波对伊朗的打击将“更残酷”，伊朗必须在被彻底摧毁前与美国达成核问题协议。特朗普当地时间13日晨在帖文中写道，美方“给了伊朗一次又一次达成协议的机会”并警告过伊朗，如果无法达成协议，伊朗受到的打击“将远超他们所知、预期或被告知的任何程度”，因为美国制造全世界最精良、最具杀伤力的军事装备，“以色列拥有大量这类装备且即将获得更多，他们更清楚如何运用这些武器”。（新华社）",
            "link": "https://www.stcn.com/article/detail/2040008.html",
            "pub_date": "2025-06-13 20:08:27",
            "source": "stcn",
            "kind": 2,
            "language": "zh-CN"
        },
        {
            "title": "天合光能：拟向控股子公司天合储能增资8亿元",
            "id": "2040011",
            "description": "人民财讯6月13日电，天合光能(688599)6月13日晚间公告，公司拟通过全资子公司天合能投向公司控股子公司江苏天合储能有限公司（简称“天合储能”）增资8亿元，天合储能其他股东放弃此次增资的优先认购权。增资完成后，公司对天合储能的控制权比例将由57.17%增至64.31%。",
            "link": "https://www.stcn.com/article/detail/2040011.html",
            "pub_date": "2025-06-13 20:10:53",
            "source": "stcn",
            "kind": 2,
            "language": "zh-CN"
        },
        {
            "title": "上交所：宁德时代H股调入港股通标的名单",
            "id": "2039980",
            "description": "人民财讯6月13日电，上交所公告称，宁德时代H股调入沪港通下港股通标的名单，并自下一港股通交易日起生效。",
            "link": "https://www.stcn.com/article/detail/2039980.html",
            "pub_date": "2025-06-13 19:51:16",
            "source": "stcn",
            "kind": 2,
            "language": "zh-CN"
        },
        {
            "title": "宏辉果蔬： 控股股东将变更为申泽瑞泰 6月16日复牌",
            "id": "2039984",
            "description": "人民财讯6月13日电，宏辉果蔬(603336)6月13日晚间公告，当日，公司控股股东、实控人黄俊辉与苏州申泽瑞泰企业管理合伙企业（有限合伙）（简称“申泽瑞泰”）签署《股份转让协议》，拟向向申泽瑞泰转让公司股份呢1.51亿股（占公司总股本的26.54%）及该等股份所对应的所有股东权利和权益，转让价格5.68元/股，合计8.6亿元。同时，黄俊辉、郑幼文与申泽瑞泰签署《表决权放弃协议》，黄俊辉放弃所持有公司股份6844.64万股（占公司总股本的12%）对应的表决权、提名权、提案权。此次权益变动完成后，公司控股股东将由黄俊辉变更为申泽瑞泰，实控人将由黄俊辉、郑幼文变更为叶桃、刘扬和苏州资产投资管理集团有限公司。公司股票6月16日复牌。",
            "link": "https://www.stcn.com/article/detail/2039984.html",
            "pub_date": "2025-06-13 19:59:42",
            "source": "stcn",
            "kind": 2,
            "language": "zh-CN"
        },
        {
            "title": "叙利亚宣布暂时关闭领空",
            "id": "2039964",
            "description": "人民财讯6月13日电，叙利亚民航局局长当地时间13日宣布，暂时关闭叙利亚领空至大马士革时间当天15时。他表示，在当前地区局势紧张的情况下，这是为确保民航安全而采取的预防措施的一部分。（央视新闻）",
            "link": "https://www.stcn.com/article/detail/2039964.html",
            "pub_date": "2025-06-13 19:41:33",
            "source": "stcn",
            "kind": 2,
            "language": "zh-CN"
        },
        {
            "title": "长春高新：子公司两款药品临床试验申请获批",
            "id": "2039966",
            "description": "人民财讯6月13日电，长春高新(000661)6月13日晚间公告，子公司金赛药业收到国家药监局核准签发的两份《药物临床试验批准通知书》，授权经销合作产品醋酸甲地孕酮口服混悬液（美适亚®）的境外生产药品注册临床试验申请获得批准；GenSci134注射液的境内生产药品注册临床试验申请获得批准。",
            "link": "https://www.stcn.com/article/detail/2039966.html",
            "pub_date": "2025-06-13 19:43:18",
            "source": "stcn",
            "kind": 2,
            "language": "zh-CN"
        },
        {
            "title": "以军继续对伊打击 以军发言人：正在为伊朗的回应做准备",
            "id": "2039967",
            "description": "人民财讯6月13日电，以色列国防军发言人埃菲·德弗林当地时间13日在新闻发布会上表示，以色列空军正在继续打击伊朗。他表示，目前以军正在继续执行攻击计划，“以实现行动目标并保卫以色列”。当被问及预计伊朗何时将向以色列发射弹道导弹时，德弗林表示“行动才刚刚开始”，并补充说军方正在“为伊朗的回应做准备”。（央视新闻）",
            "link": "https://www.stcn.com/article/detail/2039967.html",
            "pub_date": "2025-06-13 19:44:16",
            "source": "stcn",
            "kind": 2,
            "language": "zh-CN"
        },
        {
            "title": "威唐工业：转让合资公司斯诺威唐49%股权",
            "id": "2039969",
            "description": "人民财讯6月13日电，威唐工业(300707)6月13日晚间公告，公司全资子公司威唐冲压拟将所持合资公司斯诺威唐（无锡）汽车配件有限公司（简称“斯诺威唐”）49%的股权，转让给斯堪尼亚制造（中国）有限公司，交易价639.45万元。转让完成后，威唐冲压将不再持有斯诺威唐股权。此次交易是为了进一步优化公司资源配置。",
            "link": "https://www.stcn.com/article/detail/2039969.html",
            "pub_date": "2025-06-13 19:46:48",
            "source": "stcn",
            "kind": 2,
            "language": "zh-CN"
        },
        {
            "title": "武汉去年软件产业规模达3521亿元",
            "id": "2039971",
            "description": "人民财讯6月13日电，6月13日，第三届软件创新发展大会在武汉举行。大会透露，去年武汉软件产业规模突破3500亿元。在软件领域，武汉拥有国家级专精特新“小巨人”企业79家，上市企业21家，上市了国产数据库、智能网联汽车芯片等多个全国第一股。2024年武汉市软件产业规模达3521亿元，增速连续三年居全国软件名城之首。",
            "link": "https://www.stcn.com/article/detail/2039971.html",
            "pub_date": "2025-06-13 19:47:53",
            "source": "stcn",
            "kind": 2,
            "language": "zh-CN"
        },
        {
            "title": "湖北宜化：拟不低于2.22亿元挂牌转让联海煤业1.718%股权",
            "id": "2039978",
            "description": "人民财讯6月13日电，湖北宜化(000422)6月13日晚间公告，公司全资子公司内蒙宜化拟通过公开挂牌方式，转让所持有的内蒙古鄂尔多斯联海煤业有限公司（简称“联海煤业”）1.718%股权，挂牌底价2.22亿元。此次交易完成后，内蒙宜化将不再持有联海煤业股权。此次交易有利于公司聚焦主业，优化资源配置。",
            "link": "https://www.stcn.com/article/detail/2039978.html",
            "pub_date": "2025-06-13 19:50:16",
            "source": "stcn",
            "kind": 2,
            "language": "zh-CN"
        },
        {
            "title": "太原重工：拟约3亿元收购太重向明67%股权",
            "id": "2039950",
            "description": "人民财讯6月13日电，太原重工(600169)6月13日晚间公告，公司拟以现金向控股股东太重集团等收购太重集团向明智能装备股份有限公司（简称“太重向明”）67%股权，交易价格合计约3亿元。太重向明致力于散状物料长距离连续输送装备的研发和制造，主要产品为带式输送机、立体车库及相关配件。截至2025年3月31日，太重向明资产总计8.24亿元，净资产3.82亿元。2024年度营业收入6.1亿元，净利润3629.25万元。公司并购太重向明，可形成显著产业协同效应，将助力公司有效拓展现有业务版图。",
            "link": "https://www.stcn.com/article/detail/2039950.html",
            "pub_date": "2025-06-13 19:35:50",
            "source": "stcn",
            "kind": 2,
            "language": "zh-CN"
        },
        {
            "title": "安阳钢铁：控股股东获得增持专项贷款承诺函",
            "id": "2039958",
            "description": "人民财讯6月13日电，安阳钢铁(600569)6月13日晚间公告，近日，公司收到控股股东安钢集团通知，安钢集团收到浦发银行安阳分行出具的《贷款承诺函》。浦发银行承诺就增持安阳钢铁股票项目向安钢集团提供不超过6320万元的股票增持贷款，贷款期限3年。",
            "link": "https://www.stcn.com/article/detail/2039958.html",
            "pub_date": "2025-06-13 19:37:40",
            "source": "stcn",
            "kind": 2,
            "language": "zh-CN"
        },
        {
            "title": "华立科技：阳优管理拟减持公司不超0.83%股份",
            "id": "2039962",
            "description": "人民财讯6月13日电，华立科技(301011)6月13日晚间公告，公司持股0.83%的股东宿迁阳优企业管理咨询有限公司（简称“阳优管理”）计划以大宗交易、集中竞价交易方式，减持公司股份合计不超过121.68万股，即不超过公司总股本的0.83%。阳优管理系公司董事、副总经理苏永益的一致行动人。",
            "link": "https://www.stcn.com/article/detail/2039962.html",
            "pub_date": "2025-06-13 19:40:34",
            "source": "stcn",
            "kind": 2,
            "language": "zh-CN"
        },
        {
            "title": "证监会就《期货公司分类评价规定（征求意见稿）》公开征求意见",
            "id": "2039933",
            "description": "人民财讯6月13日电，为有效实施对期货公司的监督管理，合理配置监管资源，提高监管效率，引导期货公司合规经营、专注主业、提升风险管理能力和服务实体经济能力，中国证监会对《期货公司分类监管规定》进行修订，形成了《期货公司分类评价规定（征求意见稿）》，现向社会公开征求意见。征求意见稿共四十四条，重点针对近年来期货市场形势和期货行业状况的发展变化，进一步明确了期货公司分类评价的扣分标准，优化了加分标准，简化了评价流程。",
            "link": "https://www.stcn.com/article/detail/2039933.html",
            "pub_date": "2025-06-13 19:25:32",
            "source": "stcn",
            "kind": 2,
            "language": "zh-CN"
        },
        {
            "title": "日联科技：拟以收购及增资方式取得珠海九源55%股权",
            "id": "2039935",
            "description": "人民财讯6月13日电，日联科技(688531)6月13日晚间公告，公司拟6075万元收购珠海九源电力电子科技有限公司（简称“珠海九源”）45%股份，并以3000万元对珠海九源进行增资。交易完成后，公司持有珠海九源55%的股权，珠海九源成为公司控股子公司。珠海九源主营高端新能源电能变换设备及检测产品业务，此次收购有利于公司丰富现有业务和产品结构，与公司现有业务形成互补，能够有效拓展公司在工业检测领域的技术能力和业务边界，助力公司打造工业检测平台型企业。",
            "link": "https://www.stcn.com/article/detail/2039935.html",
            "pub_date": "2025-06-13 19:27:17",
            "source": "stcn",
            "kind": 2,
            "language": "zh-CN"
        },
        {
            "title": "国常会：更大力度推动房地产市场止跌回稳",
            "id": "2039936",
            "description": "人民财讯6月13日电，李强主持召开国务院常务会议，听取构建房地产发展新模式和推进好房子建设有关情况汇报。会议指出，构建房地产发展新模式，对于促进房地产市场平稳、健康、高质量发展具有重要意义，要着眼长远，坚持稳中求进、先立后破，有序搭建相关基础性制度。要扎实有力推进“好房子”建设，纳入城市更新机制加强工作统筹，在规划、土地、财政、金融等方面予以政策支持。要对全国房地产已供土地和在建项目进行摸底，进一步优化现有政策，提升政策实施的系统性有效性，多管齐下稳定预期、激活需求、优化供给、化解风险，更大力度推动房地产市场止跌回稳。（央视新闻）",
            "link": "https://www.stcn.com/article/detail/2039936.html",
            "pub_date": "2025-06-13 19:29:03",
            "source": "stcn",
            "kind": 2,
            "language": "zh-CN"
        },
        {
            "title": "安硕信息：收到政府补助款642万元",
            "id": "2039108",
            "description": "人民财讯6月13日电，安硕信息(300380)6月13日晚间公告，公司今日收到政府补助款642万元，补助金额占公司最近一期净利润的42.55%，预计对当年税前利润影响金额为642万元。",
            "link": "https://www.stcn.com/article/detail/2039108.html",
            "pub_date": "2025-06-13 19:12:02",
            "source": "stcn",
            "kind": 2,
            "language": "zh-CN"
        },
        {
            "title": "深交所：本周对141起证券异常交易行为采取自律监管措施",
            "id": "2039210",
            "description": "人民财讯6月13日电，6月9日至6月13日，深交所共对141起证券异常交易行为采取了自律监管措施，涉及盘中拉抬打压、虚假申报等异常交易情形；共对2起上市公司重大事项进行核查，并上报证监会1起涉嫌违法违规案件线索。",
            "link": "https://www.stcn.com/article/detail/2039210.html",
            "pub_date": "2025-06-13 19:12:34",
            "source": "stcn",
            "kind": 2,
            "language": "zh-CN"
        }
    ]
}