{
    "data": [
        {
            "title": "香港官员：将修例布局低空经济并为各司法管辖区作参考",
            "id": "1844380",
            "description": "人民财讯5月24日电，香港特区政府运输及物流局局长陈美宝24日发表网志称，香港将就低空经济相关法例作出修订，旨在促成香港低空经济发展的同时，让这套法律框架成为各司法管辖区发展低空经济的参考，借香港在国际航空的影响力设立世界级低空空域管理标准。（中国新闻网）",
            "link": "https://www.stcn.com/article/detail/1844380.html",
            "pub_date": "2025-05-24 21:44:37",
            "source": "stcn",
            "kind": 2,
            "language": "zh-CN"
        },
        {
            "title": "米价居高不下 日本新农相承诺投放低价储备米",
            "id": "1844379",
            "description": "人民财讯5月24日电，日本新上任的农林水产大臣小泉进次郎24日说，政府计划直接将储备米卖给零售商，而非像之前一样拍卖给中间商，希望以此平抑米价。小泉进次郎当天在札幌市发表演讲时表示，政府将绕过那些阻碍政府控制价格的拍卖机制，与零售商“直接签合同”，同时调低米价，以一袋5公斤装大米2000日元（约合101元人民币）的价格出售。日本农林水产省发布的最新数据显示，日本市场上一袋5公斤装大米均价为4268日元（约合215元人民币），是去年同期的两倍多，也是农林水产省开始统计这一数据以来的最高水平。（新华社）",
            "link": "https://www.stcn.com/article/detail/1844379.html",
            "pub_date": "2025-05-24 21:30:40",
            "source": "stcn",
            "kind": 2,
            "language": "zh-CN"
        },
        {
            "title": "俄官员：和平备忘录草案将于未来几天提交",
            "id": "1844377",
            "description": "人民财讯5月24日电，当地时间24日，俄罗斯联邦委员会（议会上院）副主席康斯坦丁·科萨切夫表示，俄罗斯将在未来几天向乌克兰转交关于和平调解备忘录框架内的阶段性技术方案。科萨切夫称，该文件的制定已经进入最后阶段。他同时表示，现阶段的这些内容将不会公开讨论。（央视新闻）",
            "link": "https://www.stcn.com/article/detail/1844377.html",
            "pub_date": "2025-05-24 20:50:26",
            "source": "stcn",
            "kind": 2,
            "language": "zh-CN"
        },
        {
            "title": "我国夏季粮油陆续收获 冬油菜已超八成",
            "id": "1844375",
            "description": "人民财讯5月24日电，我国夏季粮油陆续进入收获时节。农业农村部24日最新消息显示，截至目前，冬小麦渐次开镰，冬油菜收获已超八成。（新华社）",
            "link": "https://www.stcn.com/article/detail/1844375.html",
            "pub_date": "2025-05-24 20:17:55",
            "source": "stcn",
            "kind": 2,
            "language": "zh-CN"
        },
        {
            "title": "托育行业人才缺口近百万 全国持证保育人员约50万人",
            "id": "1844368",
            "description": "人民财讯5月24日电，记者了解到，目前市场上托育行业人才缺口较大，相关培训活动正加速展开。机构数据显示，2025年中国婴幼儿托育市场规模为1621.3亿元，预计2030年有望达2323.1亿元，年均增长率约7.5%。目前，现有托育机构仅能满足不到10%的0—3岁婴幼儿需求，而全国持证保育人员约50万人，人才缺口近100万人，尤其是对于具备婴幼儿照护、早教以及营养保健、心理学知识的复合型人才市场供给严重不足。（央视财经）",
            "link": "https://www.stcn.com/article/detail/1844368.html",
            "pub_date": "2025-05-24 19:50:53",
            "source": "stcn",
            "kind": 2,
            "language": "zh-CN"
        },
        {
            "title": "德国席勒研究所创始人：德国经济因乌克兰问题面临最严重危机",
            "id": "1844372",
            "description": "人民财讯5月24日电，据塔斯社24日报道，德国智库席勒研究所创始人拉鲁什当天表示，西方国家在支持乌克兰的问题上缺乏共识，而德国经济正因此面临最严重的危机和市场流失。此前，德国经济专家委员会21日发布经济预测报告，预计2025年德国经济零增长较此前0.4%的增长预期值明显下调，这意味着德国经济或将连续三年未能实现增长。（央视新闻）",
            "link": "https://www.stcn.com/article/detail/1844372.html",
            "pub_date": "2025-05-24 19:56:20",
            "source": "stcn",
            "kind": 2,
            "language": "zh-CN"
        },
        {
            "title": "土外长将访俄 讨论双边关系等",
            "id": "1844362",
            "description": "人民财讯5月24日电，据土耳其外交部当地时间24日声明，土耳其外长费丹将于5月26日至27日对俄罗斯进行正式访问。访问期间将与俄罗斯总统普京以及俄罗斯外长拉夫罗夫举行会谈。会谈将讨论土俄双边关系以及两国在贸易、能源、旅游等关键领域的合作举措。费丹表示，土耳其致力于为俄乌冲突提供公正和持久的调解，对近期向这一方向取得的进展表示满意。（央视新闻）",
            "link": "https://www.stcn.com/article/detail/1844362.html",
            "pub_date": "2025-05-24 19:23:19",
            "source": "stcn",
            "kind": 2,
            "language": "zh-CN"
        },
        {
            "title": "2025端午档新片预售总票房破1000万元",
            "id": "1844357",
            "description": "人民财讯5月24日电，据猫眼专业版数据，截至5月24日18时46分，2025年端午档新片预售总票房（含点映）破1000万元，《时间之子》《碟中谍8：最终清算》《私家侦探》分列2025年端午档新片预售票房前三位。",
            "link": "https://www.stcn.com/article/detail/1844357.html",
            "pub_date": "2025-05-24 18:56:37",
            "source": "stcn",
            "kind": 2,
            "language": "zh-CN"
        },
        {
            "title": "海南首条直飞沙特国际航线计划6月28日开通",
            "id": "1844354",
            "description": "人民财讯5月24日电，海南航空计划于6月28日开通海口⇌吉达直飞航线，这是海南首次开通直飞沙特阿拉伯王国的国际航线。据悉，海南航空海口⇌吉达国际航线计划每周执行3个往返航班，班期每周一、三、六。",
            "link": "https://www.stcn.com/article/detail/1844354.html",
            "pub_date": "2025-05-24 18:44:37",
            "source": "stcn",
            "kind": 2,
            "language": "zh-CN"
        },
        {
            "title": "开源鸿蒙代码规模已达1.3亿行",
            "id": "1844351",
            "description": "人民财讯5月24日电，5月24日，在开源鸿蒙开发者大会上，开源鸿蒙5.1Release版本正式发布。开源鸿蒙项目群工作委员会主席、华为终端BG软件部总裁龚体表示，开源四年多来，开源鸿蒙代码规模已达1.3亿多行，代码贡献者达8600多位，超过1100款软硬件产品通过兼容性测评，覆盖金融、交通、教育、医疗、航天等多个行业领域。（第一财经）",
            "link": "https://www.stcn.com/article/detail/1844351.html",
            "pub_date": "2025-05-24 18:30:45",
            "source": "stcn",
            "kind": 2,
            "language": "zh-CN"
        },
        {
            "title": "李家超：将香港打造成为区内的跨境电商物流配送中心",
            "id": "1844347",
            "description": "人民财讯5月24日电，香港特区行政长官李家超今天（24日）出席“购在中国·2025大湾区消费季”启动仪式并致辞。他表示将善用香港优越的地理位置，以及一流的运输物流基建设施，将香港打造成为区内的跨境电商物流配送中心。同时，会扩展“BUD专项基金”下电商易计划的资助范围，涵盖更多地区，并且透过由香港贸易发展局举办的“香港好物节“和推行新的“电子商务快线”服务，加强香港品牌在境外市场的曝光和竞争力，协助企业拓展电商业务。李家超表示，未来，香港特区政府会继续加快产业数字转型、加强数字基础建设、研究促进数据交易生态，并且以大湾区作试点探讨便利数据跨境流动安排，推动数字经济和实体经济融合发展。（大湾区之声）",
            "link": "https://www.stcn.com/article/detail/1844347.html",
            "pub_date": "2025-05-24 18:03:09",
            "source": "stcn",
            "kind": 2,
            "language": "zh-CN"
        },
        {
            "title": "四部门联合印发指导意见 推动高效办成企业迁移登记“一件事”",
            "id": "1844349",
            "description": "人民财讯5月24日电，记者今天了解到，市场监管总局会同人力资源社会保障部、住房城乡建设部、税务总局联合印发《关于推动高效办成企业迁移登记“一件事”的指导意见》，旨在通过“流程再造、系统优化、业务协同、完善规则”，解决企业迁移过程中“多头申请、多次跑动”问题，推动企业迁移登记实现“一次办、便捷办、高效办”，进一步降低企业办事成本。（央视新闻）",
            "link": "https://www.stcn.com/article/detail/1844349.html",
            "pub_date": "2025-05-24 18:06:35",
            "source": "stcn",
            "kind": 2,
            "language": "zh-CN"
        },
        {
            "title": "云鼎科技联合昇腾发布工业视觉智能一体机",
            "id": "1844338",
            "description": "人民财讯5月24日电，5月24日，云鼎科技联合昇腾重磅发布云鼎工业视觉智能一体机，这款专为工业场景量身打造的智能视觉平台，凭借“硬件+模型+平台+场景”深度融合架构 ，实现了工业大模型与边缘计算的协同创新。",
            "link": "https://www.stcn.com/article/detail/1844338.html",
            "pub_date": "2025-05-24 17:36:58",
            "source": "stcn",
            "kind": 2,
            "language": "zh-CN"
        },
        {
            "title": "第二十五届中国国际投资贸易洽谈会组委会第一次工作会在福州召开",
            "id": "1844330",
            "description": "人民财讯5月24日电，商务部消息，5月24日，第二十五届中国国际投资贸易洽谈会（以下简称投洽会）组委会第一次工作会在福建省福州市召开。投洽会由商务部主办，是以投资为主题的国家级平台，也是“投资中国”标志性展会。第二十五届投洽会将于2025年9月8—11日在厦门举办，英国将担任主宾国，江苏省将担任主宾省。本届投洽会将深入贯彻落实习近平总书记致第二十届投洽会贺信精神和扩大对外开放的系列重要讲话精神，设置“投资中国”“中国投资”“国际投资”三大板块，紧扣双向投资促进主题，促进各方互利共赢。",
            "link": "https://www.stcn.com/article/detail/1844330.html",
            "pub_date": "2025-05-24 17:09:31",
            "source": "stcn",
            "kind": 2,
            "language": "zh-CN"
        },
        {
            "title": "中欧班列（武汉）跨里海新线路直达格鲁吉亚",
            "id": "1844328",
            "description": "人民财讯5月24日电，5月24日，中欧班列（武汉—霍尔果斯—波季/第比利斯）从中铁联集武汉中心站鸣笛启航，这是中欧班列（武汉）首次将格鲁吉亚作为目的站开辟的跨里海国际运输新线路，为中欧班列（武汉）向南拓展物流通道注入了新动力。本趟班列主要装有轻型机械设备、农用车辆、建材等，货值约1482.25万元。班列从武汉出发，将从霍尔果斯口岸出境，横跨哈萨克斯坦的广袤土地，经阿克套港转轮渡穿越里海至阿塞拜疆巴库，最终以铁路运输抵达格鲁吉亚波季和第比利斯，全程采用“铁—海—铁”多式联运方式，运输时间预计为18天。（央视新闻）",
            "link": "https://www.stcn.com/article/detail/1844328.html",
            "pub_date": "2025-05-24 16:54:50",
            "source": "stcn",
            "kind": 2,
            "language": "zh-CN"
        },
        {
            "title": "第七届智能传感器产业发展大会在蚌埠开幕",
            "id": "1844327",
            "description": "人民财讯5月24日电，第七届智能传感器产业发展大会24日在蚌埠开幕。700余名专家学者和企业家出席会议。本次大会以“芯聚江淮 智感世界”为主题，聚焦智能传感器产业的前沿技术，涵盖汽车、医疗、机器人、脑机接口等多个热门应用领域，为以“芯”互联、以“智”赋能搭建了一个高水平的交流合作平台。会议发布了长三角MEMS与传感器新技术新产品，超低噪声高精度生物信号采集系列芯片、生物信号采集系列电极、可控多通道脑电采集系统等多款新产品等一批“蚌埠智造”集中亮相。会议还发布了8英寸晶圆制造线首批产品成功串线及工艺平台能力，作为国内领先的MEMS智能传感器晶圆生产线，蚌埠8英寸晶圆制造线规划产能3万片/月，预计今年年底产能可以达到1万片/月。（中国新闻网）",
            "link": "https://www.stcn.com/article/detail/1844327.html",
            "pub_date": "2025-05-24 16:34:42",
            "source": "stcn",
            "kind": 2,
            "language": "zh-CN"
        },
        {
            "title": "赛力斯与TÜV莱茵签署合作备忘录",
            "id": "1844323",
            "description": "人民财讯5月24日电，2025年5月21日，赛力斯集团股份有限公司与国际独立第三方检测、检验和认证机构德国莱茵TÜV大中华区签署合作备忘录。双方将在汽车整车、系统及零部件等领域的认证、检测检验、安全评估、质量管理及其延伸业务建立全面长期战略合作关系。",
            "link": "https://www.stcn.com/article/detail/1844323.html",
            "pub_date": "2025-05-24 16:08:45",
            "source": "stcn",
            "kind": 2,
            "language": "zh-CN"
        },
        {
            "title": "日英意六代机模型亮相日本防务展",
            "id": "1844320",
            "description": "人民财讯5月24日电，5月21日，在日本规模最大的防务装备展——2025东京军警防务展览会上，由日本、英国和意大利联合推进的“全球作战空中计划”（GCAP）首次公开其下一代战斗机模型。GCAP是日本的下一代战机计划。下一代战机被定位为“第六代战斗机”，重视高性能传感器、隐形性和网络化作战，旨在超越作为五代机代表的美国F-22和F-35隐形战机。（央视新闻）",
            "link": "https://www.stcn.com/article/detail/1844320.html",
            "pub_date": "2025-05-24 15:57:28",
            "source": "stcn",
            "kind": 2,
            "language": "zh-CN"
        },
        {
            "title": "数据显示今年赴美国际旅客数量将下降8.7%",
            "id": "1844321",
            "description": "人民财讯5月24日电，英国牛津经济研究院下属的旅游经济学公司日前发布数据显示，受美国政府出台“对等关税”等因素影响，2025年美国国际入境旅客数量将下降8.7%，其中来自加拿大、墨西哥及西欧国家的国际旅客数量降幅较大。（新华社）",
            "link": "https://www.stcn.com/article/detail/1844321.html",
            "pub_date": "2025-05-24 15:59:19",
            "source": "stcn",
            "kind": 2,
            "language": "zh-CN"
        },
        {
            "title": "特朗普在日铁与美钢交易问题上改变立场",
            "id": "1844314",
            "description": "人民财讯5月24日电，美国总统特朗普23日称，美国钢铁公司与日本制铁公司将达成“计划中的合作伙伴关系”，日铁将对美钢进行投资，而美钢将继续“留在美国”。特朗普当天在社交媒体平台“真实社交”上发文说，美钢总部将继续留在宾夕法尼亚州匹兹堡。“这将是美国钢铁与日本制铁计划中的合作伙伴关系，这一合作将创造至少7万个就业岗位，并为美国经济增加140亿美元。大部分投资将在未来14个月内完成。”（新华社）",
            "link": "https://www.stcn.com/article/detail/1844314.html",
            "pub_date": "2025-05-24 15:42:21",
            "source": "stcn",
            "kind": 2,
            "language": "zh-CN"
        }
    ]
}