{
    "data": [
        {
            "title": "泡泡玛特涨逾5% 股价创历史新高",
            "id": "1671498",
            "description": "人民财讯4月17日电，泡泡玛特午后拉升，涨逾5%，股价创历史新高。",
            "link": "https://www.stcn.com/article/detail/1671498.html",
            "pub_date": "2025-04-17 13:42:16",
            "source": "stcn",
            "kind": 2,
            "language": "zh-CN"
        },
        {
            "title": "捷强装备等投资成立材料科技公司",
            "id": "1671500",
            "description": "人民财讯4月17日电，企查查APP显示，近日，绵阳碳锋材料科技有限公司成立，法定代表人为吉学文，注册资本3000万元，经营范围包含：新材料技术研发；有色金属合金制造；有色金属合金销售；电子专用材料研发等。企查查股权穿透显示，该公司由捷强装备(300875)全资子公司北京中戎军科投资有限公司等共同持股。",
            "link": "https://www.stcn.com/article/detail/1671500.html",
            "pub_date": "2025-04-17 13:43:16",
            "source": "stcn",
            "kind": 2,
            "language": "zh-CN"
        },
        {
            "title": "电力板块震荡回升 乐山电力四连板",
            "id": "1671492",
            "description": "人民财讯4月17日电，午后电力板块震荡回升，乐山电力四连板，淮河能源涨停，韶能股份、西昌电力、闽东电力、赣能股份等跟涨。",
            "link": "https://www.stcn.com/article/detail/1671492.html",
            "pub_date": "2025-04-17 13:27:56",
            "source": "stcn",
            "kind": 2,
            "language": "zh-CN"
        },
        {
            "title": "美媒：美政府暂不支持以色列袭击伊朗核设施的计划",
            "id": "1671493",
            "description": "人民财讯4月17日电，据美国媒体16日报道，经过长时间讨论，美国政府暂不支持以色列对伊朗核设施发动袭击的计划，选择与伊朗就限制其核计划进行谈判。（新华社）",
            "link": "https://www.stcn.com/article/detail/1671493.html",
            "pub_date": "2025-04-17 13:30:17",
            "source": "stcn",
            "kind": 2,
            "language": "zh-CN"
        },
        {
            "title": "跨境电商概念拉升 电声股份20%涨停",
            "id": "1671479",
            "description": "人民财讯4月17日电，跨境电商概念拉升，电声股份20%涨停，南京商旅、浔兴股份、红蜻蜓、三柏硕此前涨停，华纺股份涨停，光云科技涨逾9%，凯淳股份涨近9%。",
            "link": "https://www.stcn.com/article/detail/1671479.html",
            "pub_date": "2025-04-17 13:10:19",
            "source": "stcn",
            "kind": 2,
            "language": "zh-CN"
        },
        {
            "title": "国电电力在广西投资成立两家驭风新能源公司",
            "id": "1671483",
            "description": "人民财讯4月17日电，企查查APP显示，近日，广西罗城驭风新能源有限公司、广西武宣驭风新能源有限公司成立，注册资本均为1000万元，经营范围均包含：发电业务、输电业务、供（配）电业务；输电、供电、受电电力设施的安装、维修和试验等。企查查股权穿透显示，两公司均由国电电力(600795)间接控股。",
            "link": "https://www.stcn.com/article/detail/1671483.html",
            "pub_date": "2025-04-17 13:13:39",
            "source": "stcn",
            "kind": 2,
            "language": "zh-CN"
        },
        {
            "title": "中国电池产品数字护照最新成果即将发布 全国首个电池数字护照注册中心将启动",
            "id": "1671486",
            "description": "人民财讯4月17日电，证券时报记者获悉，为加快推进产品数字护照探索实践，“产品数字护照（DPP）国际研讨会”拟于2025年4月25日召开。据悉，大会将发布中国电池产品数字护照成果。同时，将举办电池产品数字护照注册管理中心（江苏）启动仪式，并发布《产品数字护照（DPP）技术发展报告（2025年）》。目前，产品数字护照成为促进国际贸易便利化的关键因素。国际上，欧盟《可持续产品生态设计法规》于2024年7月正式生效，率先面向电池、纺织等行业开展产品数字护照管理工作。根据欧盟《电池与废电池法规》，从2027年2月起，轻型交通工具电池、容量超过2kWh的工业电池和电动汽车电池将必须按照要求通过DPP提供数据。",
            "link": "https://www.stcn.com/article/detail/1671486.html",
            "pub_date": "2025-04-17 13:17:46",
            "source": "stcn",
            "kind": 2,
            "language": "zh-CN"
        },
        {
            "title": "上海人工智能实验室开源通用多模态大模型书生·万象3.0",
            "id": "1671462",
            "description": "人民财讯4月17日电，4月16日，上海人工智能实验室（上海AI实验室）升级并开源了通用多模态大模型书生·万象3.0（InternVL3）。通过采用创新的多模态预训练和后训练方法，InternVL3多模态基础能力全面提升，在专家级基准测试、多模态性能全面测试中，10亿~780亿参数的全量级版本在开源模型中性能均位列第一，同时大幅提升了图形用户界面（GUI）智能体、建筑场景图纸理解、空间感知推理以及通识学科推理等方面的能力。",
            "link": "https://www.stcn.com/article/detail/1671462.html",
            "pub_date": "2025-04-17 12:43:57",
            "source": "stcn",
            "kind": 2,
            "language": "zh-CN"
        },
        {
            "title": "首个云超算国标正式发布",
            "id": "1671471",
            "description": "人民财讯4月17日电，近日，国家市场监督管理总局、国家标准化管理委员会正式发布首个云超算国家标准GB/T45400-2025，将于今年10月实施。该标准由阿里云联合中国电子技术标准化研究院等机构牵头起草，为云超算在更多高性能计算领域的大规模应用奠定基础，推动我国算力基础设施建设迈向标准化、智能化新阶段。云超算是一种新型的高性能计算（HPC），它基于云基础设施对外提供弹性可扩展的高性能计算服务。",
            "link": "https://www.stcn.com/article/detail/1671471.html",
            "pub_date": "2025-04-17 12:50:37",
            "source": "stcn",
            "kind": 2,
            "language": "zh-CN"
        },
        {
            "title": "工银瑞信FOF投资部总经理蒋华安离职",
            "id": "1671452",
            "description": "人民财讯4月17日电，4月17日工银瑞信基金公告显示，蒋华安因个人原因卸任工银养老2035(FOF)等约9只FOF的基金经理。数据显示，蒋华安名下目前已无在管基金。蒋华安已按规定在基金业协会办理注销手续。证券时报记者从业内相关渠道获悉，蒋华安从工银瑞信基金离职。离职前，蒋华安是工银瑞信基金的FOF投资部总经理，证券从业年限16年，2017年加入工银瑞信基金，此前曾是社保基金理事会资产配置处副处长。",
            "link": "https://www.stcn.com/article/detail/1671452.html",
            "pub_date": "2025-04-17 12:37:24",
            "source": "stcn",
            "kind": 2,
            "language": "zh-CN"
        },
        {
            "title": "淘宝已在16个国家App下载榜登顶",
            "id": "1671436",
            "description": "人民财讯4月17日电，据第三方数据机构统计，截至目前，淘宝已经在16个国家App下载榜上排名第一，在123个国家排名前十，大量海外消费者涌入淘宝。公开数据显示，4月12日，淘宝App海外下载量为104000，而到了4月15日，这一数字达到326000，环比12日暴涨222%。其中仅iOS平台，北美地区下载量环比12日增长了483%，欧洲则增长了439%。不少淘宝商家已经感受到海外流量暴增。",
            "link": "https://www.stcn.com/article/detail/1671436.html",
            "pub_date": "2025-04-17 12:11:41",
            "source": "stcn",
            "kind": 2,
            "language": "zh-CN"
        },
        {
            "title": "银华国证港股通创新药ETF发起式联接基金成立",
            "id": "1671440",
            "description": "人民财讯4月17日电，4月17日银华基金公告称，银华国证港股通创新药ETF发起式联接基金成立，募集规模1018.2亿元，获36户有效认购。",
            "link": "https://www.stcn.com/article/detail/1671440.html",
            "pub_date": "2025-04-17 12:12:23",
            "source": "stcn",
            "kind": 2,
            "language": "zh-CN"
        },
        {
            "title": "贝因美等成立食品贸易公司",
            "id": "1671444",
            "description": "人民财讯4月17日电，企查查APP显示，近日，天津贝源森食品贸易有限公司成立，法定代表人为文静瑶，注册资本100万元，经营范围包含：食品销售（仅销售预包装食品）；健康咨询服务（不含诊疗服务）；信息技术咨询服务等。企查查股权穿透显示，该公司由贝因美(002570)旗下贝因美（天津）科技有限公司、天津中泰恒源企业管理有限公司共同持股。",
            "link": "https://www.stcn.com/article/detail/1671444.html",
            "pub_date": "2025-04-17 12:13:12",
            "source": "stcn",
            "kind": 2,
            "language": "zh-CN"
        },
        {
            "title": "英杰电气：2025年半导体设备电源国产替代有望加速推进",
            "id": "1671426",
            "description": "人民财讯4月17日电，英杰电气(300820)在深交所互动平台上表示，半导体设备高端电源国产化率极低，刻蚀及PECVD薄膜沉积电源几乎全依赖进口。如今情况逐步改善，当下，海外对半导体设备高端电源实施限供、禁供，给国产电源带来发展空间。包括英杰电气在内的国内厂家已具备一定国产替代能力，部分型号已经批量供应重点客户，随着技术持续突破，2025年半导体设备电源的国产替代有望加速推进，同时也应注意到半导体设备其他关键部件的国产化推进情况，其国产化进度对于设备厂家的电源需求也是有影响的。",
            "link": "https://www.stcn.com/article/detail/1671426.html",
            "pub_date": "2025-04-17 12:03:55",
            "source": "stcn",
            "kind": 2,
            "language": "zh-CN"
        },
        {
            "title": "佳隆股份：酱油业务正有序推进 预计在2025年可以上市",
            "id": "1671428",
            "description": "人民财讯4月17日电，佳隆股份(002495)在深交所互动平台上表示，公司高度重视产品质量，公司的酱油业务正在有序推进中，预计在2025年可以上市。",
            "link": "https://www.stcn.com/article/detail/1671428.html",
            "pub_date": "2025-04-17 12:04:56",
            "source": "stcn",
            "kind": 2,
            "language": "zh-CN"
        },
        {
            "title": "华夏首创奥莱REIT于17日停牌一天",
            "id": "1671430",
            "description": "人民财讯4月17日电，4月17日华夏基金公告称，为了保护基金份额持有人的利益，华夏首创奥莱REIT于17日停牌一天，18日起复牌。公告显示，4月16日华夏首创奥莱REIT的二级市场收盘价为4.329元/份，当日收盘价较基准价（基金发行价2.468元/份）累计涨幅达到75.41%。",
            "link": "https://www.stcn.com/article/detail/1671430.html",
            "pub_date": "2025-04-17 12:07:53",
            "source": "stcn",
            "kind": 2,
            "language": "zh-CN"
        },
        {
            "title": "港股午评：恒生指数涨1.62% 恒生科技指数涨2.3%",
            "id": "1671432",
            "description": "人民财讯4月17日电，港股午间收盘，恒生指数涨1.62%，恒生科技指数涨2.30%。蔚来、网易、中芯国际、阿里巴巴涨超3%，腾讯控股涨超2%。",
            "link": "https://www.stcn.com/article/detail/1671432.html",
            "pub_date": "2025-04-17 12:08:29",
            "source": "stcn",
            "kind": 2,
            "language": "zh-CN"
        },
        {
            "title": "精锻科技：公司当前研发的主要是人形机器人智能关节模组关键零部件",
            "id": "1671434",
            "description": "人民财讯4月17日电，精锻科技(300258)在深交所互动平台上就人形机器人产品进度表示，公司当前在研究和开发的主要是人形机器人智能关节模组关键零部件，现尚在产品开发和技术研发阶段。",
            "link": "https://www.stcn.com/article/detail/1671434.html",
            "pub_date": "2025-04-17 12:10:28",
            "source": "stcn",
            "kind": 2,
            "language": "zh-CN"
        },
        {
            "title": "华夏恒泰64个月定开债基限购",
            "id": "1671423",
            "description": "人民财讯4月17日电，4月17日华夏基金公告称，华夏恒泰64个月定开债基在开放期（4月21日至5月21日）对申购及转换转入业务进行限制，单个投资人单日累计申购及转换转入申请的合计申请金额应不超过50万元。华夏恒泰64个月定开债基成立于2019年12月，截至2024年末规模为72.54亿元。",
            "link": "https://www.stcn.com/article/detail/1671423.html",
            "pub_date": "2025-04-17 11:59:47",
            "source": "stcn",
            "kind": 2,
            "language": "zh-CN"
        },
        {
            "title": "中国房协与中建壹品建立房建产业协作战略合作",
            "id": "1671414",
            "description": "人民财讯4月17日电，2025年4月16日，中建壹品投资公司董事长徐超等班子成员到访中国房地产业协会，与陈宜明会长等班子成员交流座谈。双方就加强房地产产业协作与创新发展达成共识，建立战略合作。",
            "link": "https://www.stcn.com/article/detail/1671414.html",
            "pub_date": "2025-04-17 11:44:59",
            "source": "stcn",
            "kind": 2,
            "language": "zh-CN"
        }
    ]
}